fasttower/__init__.py
fasttower/admin/__init__.py
fasttower/admin/site.py
fasttower/admin/templates/base.html
fasttower/admin/templates/dashboard.html
fasttower/admin/templates/layout.html
fasttower/apps/__init__.py
fasttower/apps/config.py
fasttower/apps/taerich/__init__.py
fasttower/apps/taerich/config.py
fasttower/auth/__init__.py
fasttower/auth/base_user.py
fasttower/auth/config.py
fasttower/auth/hashers.py
fasttower/auth/models.py
fasttower/auth/providers.py
fasttower/blueprints/__init__.py
fasttower/blueprints/commands.py
fasttower/blueprints/templates/app/__init__.py.jinja
fasttower/blueprints/templates/app/admin.py.jinja
fasttower/blueprints/templates/app/config.py.jinja
fasttower/blueprints/templates/app/models.py.jinja
fasttower/blueprints/templates/app/routers.py.jinja
fasttower/blueprints/templates/app/serializers.py.jinja
fasttower/blueprints/templates/app/views.py.jinja
fasttower/blueprints/templates/project/manage.py.jinja
fasttower/blueprints/templates/project/project_name/__init__.py.jinja
fasttower/blueprints/templates/project/project_name/asgi.py.jinja
fasttower/blueprints/templates/project/project_name/routers.py.jinja
fasttower/blueprints/templates/project/project_name/settings.py.jinja
fasttower/cache/__init__.py
fasttower/cache/backends.py
fasttower/cache/lifespan.py
fasttower/cli.py
fasttower/conf/__init__.py
fasttower/conf/global_settings.py
fasttower/db/__init__.py
fasttower/db/commands.py
fasttower/db/lifespan.py
fasttower/db/models/__init__.py
fasttower/email/__init__.py
fasttower/email/backends.py
fasttower/exceptions.py
fasttower/generics/__init__.py
fasttower/mixins/__init__.py
fasttower/routers/__init__.py
fasttower/serializers/__init__.py
fasttower/server.py
fasttower/utils/__init__.py
fasttower/views/__init__.py
LICENSE
README.md
fasttower-0.1.6.dist-info/entry_points.txt
fasttower-0.1.6.dist-info/LICENSE
fasttower-0.1.6.dist-info/METADATA
fasttower-0.1.6.dist-info/WHEEL
fasttower-0.1.6.dist-info/RECORD
