Metadata-Version: 2.1
Name: fasttower
Version: 0.1.6
Summary: A Django-like framework built on FastAPI
Home-page: https://github.com/pysashapy/fasttower
License: MIT
Keywords: python,api,framework,web,rest,async,swagger,python3,asyncio,easy-web,starlette,fastapi,fasttower
Author: Alexander Ibragmov
Author-email: sasha.2000ibr@gmail.com
Requires-Python: >=3.10,<4.0
Classifier: Framework :: FastTower
Classifier: License :: OSI Approved :: MIT License
Classifier: Operating System :: OS Independent
Classifier: Programming Language :: Python :: 3
Classifier: Programming Language :: Python :: 3.10
Classifier: Programming Language :: Python :: 3.11
Classifier: Programming Language :: Python :: 3.12
Classifier: Programming Language :: Python :: 3.13
Provides-Extra: tortoise
Requires-Dist: Jinja2 (>=3.1.4,<4.0.0)
Requires-Dist: aiosmtplib (>=3.0.2,<4.0.0)
Requires-Dist: fastapi (>=0.115.0,<0.116.0)
Requires-Dist: fastapi-admin (>=1.0.4,<2.0.0) ; extra == "tortoise"
Requires-Dist: fastapi-cache2 (>=0.2.2,<0.3.0)
Requires-Dist: fastapi-debug-toolbar (>=0.6.3,<0.7.0)
Requires-Dist: ipython (>=8.27.0,<9.0.0)
Requires-Dist: itsdangerous (>=2.2.0,<3.0.0)
Requires-Dist: redis (>=5.2.0,<6.0.0)
Requires-Dist: scrypt (>=0.8.24,<0.9.0)
Requires-Dist: tortoise-orm (>=0.21.7,<0.22.0) ; extra == "tortoise"
Requires-Dist: typer (>=0.12.5,<0.13.0)
Requires-Dist: uvicorn (>=0.30.6,<0.31.0)
Project-URL: Bug Tracker, https://github.com/pysashapy/fasttower/issues
Project-URL: Documentation, https://pysashapy.github.io/fasttower
Project-URL: Repository, https://github.com/pysashapy/fasttower.git
